web2db/__init__.py
web2db-0.1.5.dist-info/METADATA
web2db-0.1.5.dist-info/WHEEL
web2db-0.1.5.dist-info/top_level.txt
web2db-0.1.5.dist-info/RECORD
