Metadata-Version: 2.1
Name: web2db
Version: 0.1.5
Summary: Fetch webpage full-text, persist link and full text to SQLITE3 db, resumable with tqdm progressbar.
Home-page: https://github.com/pushkarparanjpe/web2db
Author: Pushkar Paranjpe
Author-email: pushkarparanjpe@gmail.com
License: MIT
Platform: UNKNOWN
